fa_transformer/__init__.py
fa_transformer/transformers.py
fa_transformer-0.1.2.dist-info/LICENSE
fa_transformer-0.1.2.dist-info/METADATA
fa_transformer-0.1.2.dist-info/WHEEL
fa_transformer-0.1.2.dist-info/top_level.txt
fa_transformer-0.1.2.dist-info/RECORD
