Metadata-Version: 2.1
Name: fa-transformer
Version: 0.1.2
Summary: A package containing custom Factor Analysis Transformers
Home-page: https://github.com/rounakbanik/fa_transformer
Author: Rounak Banik
Author-email: rounakbanik@gmail.com
License: MIT
Platform: UNKNOWN
Classifier: Development Status :: 3 - Alpha
Classifier: Intended Audience :: Science/Research
Classifier: License :: OSI Approved :: MIT License
Classifier: Programming Language :: Python :: 3
Classifier: Programming Language :: Python :: 3.4
Classifier: Programming Language :: Python :: 3.5
Requires-Dist: numpy
Requires-Dist: sklearn
Requires-Dist: pandas
Requires-Dist: factor-analyzer
